<h:html xmlns="http://www.w3.org/2002/xforms"
  xmlns:h="http://www.w3.org/1999/xhtml"
  xmlns:xsd="http://www.w3.org/2001/XMLSchema"
  xmlns:jr="http://openrosa.org/javarosa">
  <h:head>
    <h:title>1. OEM grupo v5 Moçambique</h:title>
    <model>
      <instance>
        <data id="OEMClusterv5_2_Mozambique.pt">
          <meta>
            <instanceID/>
          </meta>
          <c_StartTime/>
          <c_EndTime/>
          <c_RecorderID/>
          <c_DistrictID/>
          <c_ClusterName/>
          <c_ClusterID/>
          <c_GPS/>
          <c_VillagePop/>
          <c_BlackFly/>
          <c_ClusterNotes/>
        </data>
      </instance>
      <itext>
        <translation lang="Portuguese">
          <text id="/data/c_RecorderID:label">
            <value>Digite o código de registo</value>
          </text>
          <text id="/data/c_RecorderID:hint">
            <value>Código de 2 dígitos atribuído a você</value>
          </text>
          <text id="/data/c_RecorderID:requiredMsg">
            <value></value>
          </text>

          <!-- District label begin -->


          <!-- District label end -->


          <text id="/data/c_ClusterName:label">
            <value>Insira o nome do grupo</value>
          </text>

          <text id="/data/c_ClusterID:hint">
            <value>exemplo: A100, D5, SP300</value>
          </text>
          <text id="/data/c_GPS:label">
            <value>Colectar coordenadas de GPS</value>
          </text>
          <text id="/data/c_GPS:hint">
            <value>Funciona melhor fora dos edifícios</value>
          </text>
          <text id="/data/c_VillagePop:label">
            <value>Insira a população do grupo da Aldeia (grupo)</value>
          </text>
          <text id="/data/c_VillagePop:hint">
            <value>Por favor, obtenha esta informação a partir do registo do MDA da comunidade</value>
          </text>
          <text id="/data/c_BlackFly:label">
            <value>Confirme a presença de mosca preta na comunidade ou perto dela</value>
          </text>
          <text id="/data/c_BlackFly:option0">
            <value>Sim</value>
          </text>
          <text id="/data/c_BlackFly:option1">
            <value>Não</value>
          </text>
          <text id="/data/c_BlackFly:option2">
            <value>Não sei</value>
          </text>
          <text id="/data/c_ClusterNotes:label">
            <value>Notas adicionais</value>
          </text>


                    <text id="/data/c_ClusterID/B1:label">
                        <value>B1 (Calandani)</value>
                    </text>
                    <text id="/data/c_ClusterID/A300:label">
                        <value>A300 (Primeria linha de villarejo)</value>
                    </text>
                    <text id="/data/c_ClusterID:option20">
                        <value>E100 (Primeria linha de villarejo)</value>
                    </text>
                    <text id="/data/c_ClusterID:option21">
                        <value>E200 (Primeria linha de villarejo)</value>
                    </text>
                    <text id="/data/c_ClusterID:option22">
                        <value>E300 (Primeria linha de villarejo)</value>
                    </text>
                    <text id="/data/c_ClusterID:option23">
                        <value>E400 (Primeria linha de villarejo)</value>
                    </text>
                    <text id="/data/c_ClusterID/A18:label">
                        <value>A18 (Unidade 3)</value>
                    </text>
                    <text id="/data/c_ClusterID:option25">
                        <value>F100 (Primeria linha de villarejo)</value>
                    </text>
                    <text id="/data/c_ClusterID:option26">
                        <value>F200 (Primeria linha de villarejo)</value>
                    </text>
                    <text id="/data/c_ClusterID:option27">
                        <value>F300 (Primeria linha de villarejo)</value>
                    </text>
                    <text id="/data/c_ClusterID:option28">
                        <value>F400 (Primeria linha de villarejo)</value>
                    </text>
                    <text id="/data/c_ClusterID:option29">
                        <value>F500 (Primeria linha de villarejo)</value>
                    </text>
                    <text id="/data/c_ClusterID/E200:label">
                        <value>E200 (Primeria linha de villarejo)</value>
                    </text>
                    <text id="/data/c_ClusterID/A9:label">
                        <value>A9 (Josina Machel)</value>
                    </text>
                    <text id="/data/c_ClusterID/D2:label">
                        <value>D2 (Chitimbe)</value>
                    </text>
                    <text id="/data/c_ClusterID/F17:label">
                        <value>F17 (Nharine)</value>
                    </text>
                    <text id="/data/c_ClusterID/G14:label">
                        <value>G14 (Nduica)</value>
                    </text>
                    <text id="/data/c_ClusterID:option130">
                        <value>E11 (Ngema-Sede)</value>
                    </text>
                    <text id="/data/c_ClusterID:option99">
                        <value>C20 (Towererani)</value>
                    </text>
                    <text id="/data/c_ClusterID:option98">
                        <value>C19 (Stakhani 1)</value>
                    </text>
                    <text id="/data/c_ClusterID/F200:label">
                        <value>F200 (Primeria linha de villarejo)</value>
                    </text>
                    <text id="/data/c_ClusterID:option95">
                        <value>C16 (Nhamalemba)</value>
                    </text>
                    <text id="/data/c_ClusterID:option94">
                        <value>C15 (Mukanga)</value>
                    </text>
                    <text id="/data/c_ClusterID:option97">
                        <value>C18 (Nteme/Nhanseula)</value>
                    </text>
                    <text id="/data/c_ClusterID:option96">
                        <value>C17 (Nkhamba 2)</value>
                    </text>
                    <text id="/data/c_ClusterID:option91">
                        <value>C12 (Malambwe)</value>
                    </text>
                    <text id="/data/c_ClusterID:option90">
                        <value>C11 (Lemberane)</value>
                    </text>
                    <text id="/data/c_ClusterID:option93">
                        <value>C14 (Mpandadzi)</value>
                    </text>
                    <text id="/data/c_ClusterID:option92">
                        <value>C13 (Massica 1&amp;2)</value>
                    </text>
                    <text id="/data/c_ClusterID:option135">
                        <value>E16 (Tengondiguere/Bororo)</value>
                    </text>
                    <text id="/data/c_ClusterID/C10:label">
                        <value>C10 (Kawero-Sede)</value>
                    </text>
                    <text id="/data/c_ClusterID/C8:label">
                        <value>C8 (Cope 1)</value>
                    </text>
                    <text id="/data/c_ClusterID/F12:label">
                        <value>F12 (Muandje)</value>
                    </text>
                    <text id="/data/c_ClusterID/G16:label">
                        <value>G16 (Ngongoti)</value>
                    </text>
                    <text id="/data/c_ClusterID/F13:label">
                        <value>F13 (Namachila)</value>
                    </text>
                    <text id="/data/c_ClusterID/G4:label">
                        <value>G4 (Calolene)</value>
                    </text>
                    <text id="/data/c_ClusterID/C9:label">
                        <value>C9 (Kamwankhuko)</value>
                    </text>
                    <text id="/data/c_ClusterID:option24">
                        <value>E500 (Primeria linha de villarejo)</value>
                    </text>
                    <text id="/data/c_ClusterID:option111">
                        <value>D12 (Muela)</value>
                    </text>
                    <text id="/data/c_ClusterID:option110">
                        <value>D11 (Muecua)</value>
                    </text>
                    <text id="/data/c_ClusterID/D7:label">
                        <value>D7 (Maunda)</value>
                    </text>
                    <text id="/data/c_ClusterID:option112">
                        <value>D13 (Muhomua)</value>
                    </text>
                    <text id="/data/c_ClusterID:option115">
                        <value>D16 (Nancuenha)</value>
                    </text>
                    <text id="/data/c_ClusterID:option114">
                        <value>D15 (Nampande)</value>
                    </text>
                    <text id="/data/c_ClusterID:option117">
                        <value>D18 (Nchamuaha)</value>
                    </text>
                    <text id="/data/c_ClusterID/G500:label">
                        <value>G500 (Primeria linha de villarejo)</value>
                    </text>
                    <text id="/data/c_ClusterID:option119">
                        <value>D20 (Thamalea)</value>
                    </text>
                    <text id="/data/c_ClusterID:option118">
                        <value>D19 (Sale)</value>
                    </text>
                    <text id="/data/c_ClusterID/F6:label">
                        <value>F6 (Fabrica)</value>
                    </text>
                    <text id="/data/c_ClusterID/D17:label">
                        <value>D17 (Nanhumba)</value>
                    </text>
                    <text id="/data/c_ClusterID/E11:label">
                        <value>E11 (Ngema-Sede)</value>
                    </text>
                    <text id="/data/c_ClusterID/F15:label">
                        <value>F15 (Nangir)</value>
                    </text>
                    <text id="/data/c_ClusterID:option141">
                        <value>F2 (Banque)</value>
                    </text>
                    <text id="/data/c_ClusterID/D9:label">
                        <value>D9 (Muanheue)</value>
                    </text>
                    <text id="/data/c_ClusterID/F20:label">
                        <value>F20 (Suze-Sede/JO)</value>
                    </text>
                    <text id="/data/c_ClusterID:option145">
                        <value>F6 (Fabrica)</value>
                    </text>
                    <text id="/data/c_ClusterID/E500:label">
                        <value>E500 (Primeria linha de villarejo)</value>
                    </text>
                    <text id="/data/c_ClusterID/A4:label">
                        <value>A4 (Cawawa)</value>
                    </text>
                    <text id="/data/c_ClusterID/B15:label">
                        <value>B15 (Ncape)</value>
                    </text>
                    <text id="/data/c_ClusterID:option164">
                        <value>G5 (Chilapitangongo)</value>
                    </text>
                    <text id="/data/c_ClusterID/G300:label">
                        <value>G300 (Primeria linha de villarejo)</value>
                    </text>
                    <text id="/data/c_ClusterID:option166">
                        <value>G7 (Hwombe)</value>
                    </text>
                    <text id="/data/c_ClusterID:option167">
                        <value>G8 (Lipende)</value>
                    </text>
                    <text id="/data/c_ClusterID:option160">
                        <value>G1 (Antigos Combatentes)</value>
                    </text>
                    <text id="/data/c_ClusterID:option161">
                        <value>G2 (Bagarila)</value>
                    </text>
                    <text id="/data/c_ClusterID:option162">
                        <value>G3 (Caia)</value>
                    </text>
                    <text id="/data/c_ClusterID:option163">
                        <value>G4 (Calolene)</value>
                    </text>
                    <text id="/data/c_ClusterID:option168">
                        <value>G9 (Macaloge-Sede)</value>
                    </text>
                    <text id="/data/c_ClusterID/E19:label">
                        <value>E19 (Uauaria)</value>
                    </text>
                    <text id="/data/c_DistrictID/Maravia:label">
                        <value>Marávia</value>
                    </text>
                    <text id="/data/c_ClusterID/B10:label">
                        <value>B10 (Mefululuchi)</value>
                    </text>
                    <text id="/data/c_ClusterID/F3:label">
                        <value>F3 (Caixote)</value>
                    </text>
                    <text id="/data/c_ClusterID/F11:label">
                        <value>F11 (Muandiua-Sede)</value>
                    </text>
                    <text id="/data/c_ClusterID/E100:label">
                        <value>E100 (Primeria linha de villarejo)</value>
                    </text>
                    <text id="/data/c_ClusterID/C2:label">
                        <value>C2 (Baulene/Greta)</value>
                    </text>
                    <text id="/data/c_ClusterID/F18:label">
                        <value>F18 (Pringo)</value>
                    </text>
                    <text id="/data/c_ClusterID:option68">
                        <value>B9 (Mbueca)</value>
                    </text>
                    <text id="/data/c_ClusterID:option69">
                        <value>B10 (Mefululuchi)</value>
                    </text>
                    <text id="/data/c_ClusterID:option64">
                        <value>B5 (Kango)</value>
                    </text>
                    <text id="/data/c_ClusterID:option65">
                        <value>B6 (Liona)</value>
                    </text>
                    <text id="/data/c_ClusterID:option66">
                        <value>B7 (Lutombochi)</value>
                    </text>
                    <text id="/data/c_ClusterID:option67">
                        <value>B8 (Mazogo Issa)</value>
                    </text>
                    <text id="/data/c_ClusterID:option60">
                        <value>B1 (Calandani)</value>
                    </text>
                    <text id="/data/c_ClusterID:option61">
                        <value>B2 (Chidjidji)</value>
                    </text>
                    <text id="/data/c_ClusterID:option62">
                        <value>B3 (Chigoma)</value>
                    </text>
                    <text id="/data/c_ClusterID:option63">
                        <value>B4 (Junta 1)</value>
                    </text>
                    <text id="/data/c_ClusterID/F100:label">
                        <value>F100 (Primeria linha de villarejo)</value>
                    </text>
                    <text id="/data/c_ClusterID:option169">
                        <value>G10 (Malemia)</value>
                    </text>
                    <text id="/data/c_ClusterID/G11:label">
                        <value>G11 (Maoga)</value>
                    </text>
                    <text id="/data/c_ClusterID/B14:label">
                        <value>B14 (Mitondo)</value>
                    </text>
                    <text id="/data/c_ClusterID/B500:label">
                        <value>B500 (Primeria linha de villarejo)</value>
                    </text>
                    <text id="/data/c_ClusterID/A10:label">
                        <value>A10 (Nhamidzi-Sede)</value>
                    </text>
                    <text id="/data/c_ClusterID/B5:label">
                        <value>B5 (Kango)</value>
                    </text>
                    <text id="/data/c_ClusterID/G8:label">
                        <value>G8 (Lipende)</value>
                    </text>
                    <text id="/data/c_ClusterID/F400:label">
                        <value>F400 (Primeria linha de villarejo)</value>
                    </text>
                    <text id="/data/c_ClusterID/A17:label">
                        <value>A17 (Unidade 1)</value>
                    </text>
                    <text id="/data/c_ClusterID:option128">
                        <value>E9 (Nampinga)</value>
                    </text>
                    <text id="/data/c_ClusterID:option129">
                        <value>E10 (Namurrobua)</value>
                    </text>
                    <text id="/data/c_ClusterID:option120">
                        <value>E1 (Chirambere)</value>
                    </text>
                    <text id="/data/c_ClusterID:option121">
                        <value>E2 (Comuendo)</value>
                    </text>
                    <text id="/data/c_ClusterID:option122">
                        <value>E3 (Gerenge/Zona Nkuruba)</value>
                    </text>
                    <text id="/data/c_ClusterID:option123">
                        <value>E4 (Gurai)</value>
                    </text>
                    <text id="/data/c_ClusterID/E2:label">
                        <value>E2 (Comuendo)</value>
                    </text>
                    <text id="/data/c_ClusterID:option125">
                        <value>E6 (Licuide)</value>
                    </text>
                    <text id="/data/c_ClusterID:option126">
                        <value>E7 (Mosquito)</value>
                    </text>
                    <text id="/data/c_ClusterID:option127">
                        <value>E8 (Naculula 2)</value>
                    </text>
                    <text id="/data/c_DistrictID:option6">
                        <value>Sanga</value>
                    </text>
                    <text id="/data/c_DistrictID:option7">
                        <value>Outro distrito</value>
                    </text>
                    <text id="/data/c_DistrictID:option4">
                        <value>Milange</value>
                    </text>
                    <text id="/data/c_DistrictID:option5">
                        <value>Morrumbala</value>
                    </text>
                    <text id="/data/c_DistrictID:option2">
                        <value>Marávia</value>
                    </text>
                    <text id="/data/c_DistrictID:option3">
                        <value>Mecanhelas</value>
                    </text>
                    <text id="/data/c_DistrictID:option0">
                        <value>Cahora-Bassa</value>
                    </text>
                    <text id="/data/c_DistrictID:option1">
                        <value>Lago</value>
                    </text>
                    <text id="/data/c_ClusterID/D100:label">
                        <value>D100 (Primeria linha de villarejo)</value>
                    </text>
                    <text id="/data/c_ClusterID/G200:label">
                        <value>G200 (Primeria linha de villarejo)</value>
                    </text>
                    <text id="/data/c_ClusterID/D15:label">
                        <value>D15 (Nampande)</value>
                    </text>
                    <text id="/data/c_ClusterID/B18:label">
                        <value>B18 (N'Nane)</value>
                    </text>
                    <text id="/data/c_ClusterID/A6:label">
                        <value>A6 (Joaquim Chissano)</value>
                    </text>
                    <text id="/data/c_ClusterID/A8:label">
                        <value>A8 (Josina Machel)</value>
                    </text>
                    <text id="/data/c_ClusterID/B100:label">
                        <value>B100 (Primeria linha de villarejo)</value>
                    </text>
                    <text id="/data/c_ClusterID/D6:label">
                        <value>D6 (Manhungua)</value>
                    </text>
                    <text id="/data/c_ClusterID/SP200:label">
                        <value>SP200 (Primeria linha de villarejo)</value>
                    </text>
                    <text id="/data/c_ClusterID/D3:label">
                        <value>D3 (Cuvinhe)</value>
                    </text>
                    <text id="/data/c_ClusterID/D20:label">
                        <value>D20 (Thamalea)</value>
                    </text>
                    <text id="/data/c_ClusterID/B19:label">
                        <value>B19 (Ntumba)</value>
                    </text>
                    <text id="/data/c_ClusterID/F2:label">
                        <value>F2 (Banque)</value>
                    </text>
                    <text id="/data/c_ClusterID/D19:label">
                        <value>D19 (Sale)</value>
                    </text>
                    <text id="/data/c_ClusterID:option15">
                        <value>D100 (Primeria linha de villarejo)</value>
                    </text>
                    <text id="/data/c_ClusterID:option14">
                        <value>C500 (Primeria linha de villarejo)</value>
                    </text>
                    <text id="/data/c_ClusterID:option17">
                        <value>D300 (Primeria linha de villarejo)</value>
                    </text>
                    <text id="/data/c_ClusterID:option16">
                        <value>D200 (Primeria linha de villarejo)</value>
                    </text>
                    <text id="/data/c_ClusterID:option11">
                        <value>C200 (Primeria linha de villarejo)</value>
                    </text>
                    <text id="/data/c_ClusterID/C13:label">
                        <value>C13 (Massica 1&amp;2)</value>
                    </text>
                    <text id="/data/c_ClusterID:option13">
                        <value>C400 (Primeria linha de villarejo)</value>
                    </text>
                    <text id="/data/c_ClusterID:option12">
                        <value>C300 (Primeria linha de villarejo)</value>
                    </text>
                    <text id="/data/c_ClusterID:option19">
                        <value>D500 (Primeria linha de villarejo)</value>
                    </text>
                    <text id="/data/c_ClusterID:option18">
                        <value>D400 (Primeria linha de villarejo)</value>
                    </text>
                    <text id="/data/c_ClusterID/E5:label">
                        <value>E5 (Jumbe)</value>
                    </text>
                    <text id="/data/c_ClusterID/D12:label">
                        <value>D12 (Muela)</value>
                    </text>
                    <text id="/data/c_ClusterID:option82">
                        <value>C3 (Beni)</value>
                    </text>
                    <text id="/data/c_ClusterID:option83">
                        <value>C4 (Cachere-Sede)</value>
                    </text>
                    <text id="/data/c_ClusterID:option80">
                        <value>C1 (Assiteni/Draiva)</value>
                    </text>
                    <text id="/data/c_ClusterID:option81">
                        <value>C2 (Baulene/Greta)</value>
                    </text>
                    <text id="/data/c_ClusterID:option86">
                        <value>C7 (Chisseche-Sede/Capingo)</value>
                    </text>
                    <text id="/data/c_ClusterID:option87">
                        <value>C8 (Cope 1)</value>
                    </text>
                    <text id="/data/c_ClusterID:option84">
                        <value>C5 (Chicadzacuane/Gaule/Mabulosse/Kakhuta)</value>
                    </text>
                    <text id="/data/c_ClusterID:option85">
                        <value>C6 (Chingambwa)</value>
                    </text>
                    <text id="/data/c_ClusterID/SP100:label">
                        <value>SP100 (Primeria linha de villarejo)</value>
                    </text>
                    <text id="/data/c_ClusterID:option89">
                        <value>C10 (Kawero-Sede)</value>
                    </text>
                    <text id="/data/c_ClusterID/F14:label">
                        <value>F14 (Namaunde)</value>
                    </text>
                    <text id="/data/c_ClusterID/G18:label">
                        <value>G18 (Njesse)</value>
                    </text>
                    <text id="/data/c_ClusterID/F9:label">
                        <value>F9 (Manso-Sede)</value>
                    </text>
                    <text id="/data/c_DistrictID/Sanga:label">
                        <value>Sanga</value>
                    </text>
                    <text id="/data/c_ClusterID/A3:label">
                        <value>A3 (Cahoue)</value>
                    </text>
                    <text id="/data/c_ClusterID/D400:label">
                        <value>D400 (Primeria linha de villarejo)</value>
                    </text>
                    <text id="/data/c_ClusterID:option124">
                        <value>E5 (Jumbe)</value>
                    </text>
                    <text id="/data/c_ClusterID/C300:label">
                        <value>C300 (Primeria linha de villarejo)</value>
                    </text>
                    <text id="/data/c_ClusterID/B13:label">
                        <value>B13 (Micucué)</value>
                    </text>
                    <text id="/data/c_ClusterID/F1:label">
                        <value>F1 (Alfazema)</value>
                    </text>
                    <text id="/data/c_ClusterID/E3:label">
                        <value>E3 (Gerenge/Zona Nkuruba)</value>
                    </text>
                    <text id="/data/c_ClusterID/A400:label">
                        <value>A400 (Primeria linha de villarejo)</value>
                    </text>
                    <text id="/data/c_ClusterID:option32">
                        <value>G300 (Primeria linha de villarejo)</value>
                    </text>
                    <text id="/data/c_ClusterID/E1:label">
                        <value>E1 (Chirambere)</value>
                    </text>
                    <text id="/data/c_ClusterID/G15:label">
                        <value>G15 (Ngange)</value>
                    </text>
                    <text id="/data/c_DistrictID/Cahora-Bassa:label">
                        <value>Cahora-Bassa</value>
                    </text>
                    <text id="/data/c_ClusterID/D200:label">
                        <value>D200 (Primeria linha de villarejo)</value>
                    </text>
                    <text id="/data/c_ClusterID/C20:label">
                        <value>C20 (Towererani)</value>
                    </text>
                    <text id="/data/c_ClusterID:option113">
                        <value>D14 (Nacaca)</value>
                    </text>
                    <text id="/data/c_ClusterID/A1:label">
                        <value>A1 (4 de Outubro)</value>
                    </text>
                    <text id="/data/c_ClusterID/E400:label">
                        <value>E400 (Primeria linha de villarejo)</value>
                    </text>
                    <text id="/data/c_ClusterID:option116">
                        <value>D17 (Nanhumba)</value>
                    </text>
                    <text id="/data/c_ClusterID:option177">
                        <value>G18 (Njesse)</value>
                    </text>
                    <text id="/data/c_ClusterID:option176">
                        <value>G17 (Nhamuedje)</value>
                    </text>
                    <text id="/data/c_ClusterID:option175">
                        <value>G16 (Ngongoti)</value>
                    </text>
                    <text id="/data/c_ClusterID:option174">
                        <value>G15 (Ngange)</value>
                    </text>
                    <text id="/data/c_ClusterID:option173">
                        <value>G14 (Nduica)</value>
                    </text>
                    <text id="/data/c_ClusterID:option172">
                        <value>G13 (Nao Aplicavel)</value>
                    </text>
                    <text id="/data/c_ClusterID:option171">
                        <value>G12 (Maundjidi)</value>
                    </text>
                    <text id="/data/c_ClusterID:option170">
                        <value>G11 (Maoga)</value>
                    </text>
                    <text id="/data/c_ClusterID/G13:label">
                        <value>G13 (Nao Aplicavel)</value>
                    </text>
                    <text id="/data/c_ClusterID/C5:label">
                        <value>C5 (Chicadzacuane/Gaule/Mabulosse/Kakhuta)</value>
                    </text>
                    <text id="/data/c_ClusterID:option179">
                        <value>G20 (Selenge)</value>
                    </text>
                    <text id="/data/c_ClusterID:option178">
                        <value>G19 (Nsoca)</value>
                    </text>
                    <text id="/data/c_ClusterID/C3:label">
                        <value>C3 (Beni)</value>
                    </text>
                    <text id="/data/c_ClusterID/D500:label">
                        <value>D500 (Primeria linha de villarejo)</value>
                    </text>
                    <text id="/data/c_ClusterID/C19:label">
                        <value>C19 (Stakhani 1)</value>
                    </text>
                    <text id="/data/c_ClusterID/B9:label">
                        <value>B9 (Mbueca)</value>
                    </text>
                    <text id="/data/c_ClusterID/A7:label">
                        <value>A7 (Josina Machel)</value>
                    </text>
                    <text id="/data/c_ClusterID/G100:label">
                        <value>G100 (Primeria linha de villarejo)</value>
                    </text>
                    <text id="/data/c_ClusterID/C12:label">
                        <value>C12 (Malambwe)</value>
                    </text>
                    <text id="/data/c_ClusterID/B20:label">
                        <value>B20 (Tulo Cambona)</value>
                    </text>
                    <text id="/data/c_ClusterID/E8:label">
                        <value>E8 (Naculula 2)</value>
                    </text>
                    <text id="/data/c_ClusterID/D18:label">
                        <value>D18 (Nchamuaha)</value>
                    </text>
                    <text id="/data/c_ClusterID/C7:label">
                        <value>C7 (Chisseche-Sede/Capingo)</value>
                    </text>
                    <text id="/data/c_ClusterID:option51">
                        <value>A12 (Quarteirao 1)</value>
                    </text>
                    <text id="/data/c_ClusterID/E15:label">
                        <value>E15 (Tengondiguere)</value>
                    </text>
                    <text id="/data/c_DistrictID/Morrumbala:label">
                        <value>Morrumbala</value>
                    </text>
                    <text id="/data/c_ClusterID:option52">
                        <value>A13 (Quarteirão 1)</value>
                    </text>
                    <text id="/data/c_ClusterID:option55">
                        <value>A16 (Unidade 1)</value>
                    </text>
                    <text id="/data/c_ClusterID:option54">
                        <value>A15 (Quarteirão 3)</value>
                    </text>
                    <text id="/data/c_ClusterID:option57">
                        <value>A18 (Unidade 3)</value>
                    </text>
                    <text id="/data/c_ClusterID:option56">
                        <value>A17 (Unidade 1)</value>
                    </text>
                    <text id="/data/c_ClusterID:option59">
                        <value>A20 (Unidade 73)</value>
                    </text>
                    <text id="/data/c_ClusterID:option58">
                        <value>A19 (Unidade 3)</value>
                    </text>
                    <text id="/data/c_ClusterID/F7:label">
                        <value>F7 (Magamba)</value>
                    </text>
                    <text id="/data/c_ClusterID/C1:label">
                        <value>C1 (Assiteni/Draiva)</value>
                    </text>
                    <text id="/data/c_ClusterID/A15:label">
                        <value>A15 (Quarteirão 3)</value>
                    </text>
                    <text id="/data/c_ClusterID/A16:label">
                        <value>A16 (Unidade 1)</value>
                    </text>
                    <text id="/data/c_ClusterID/G20:label">
                        <value>G20 (Selenge)</value>
                    </text>
                    <text id="/data/c_ClusterID/D14:label">
                        <value>D14 (Nacaca)</value>
                    </text>
                    <text id="/data/c_ClusterID/C11:label">
                        <value>C11 (Lemberane)</value>
                    </text>
                    <text id="/data/c_ClusterID/F10:label">
                        <value>F10 (Marrundo)</value>
                    </text>
                    <text id="/data/c_ClusterID/E17:label">
                        <value>E17 (Tengondiguere/Chingoma)</value>
                    </text>
                    <text id="/data/c_ClusterID:option139">
                        <value>E20 (Wilsone-Sede)</value>
                    </text>
                    <text id="/data/c_ClusterID:option138">
                        <value>E19 (Uauaria)</value>
                    </text>
                    <text id="/data/c_ClusterID:option133">
                        <value>E14 (Nkango)</value>
                    </text>
                    <text id="/data/c_ClusterID:option132">
                        <value>E13 (Nguale/Podogoma)</value>
                    </text>
                    <text id="/data/c_ClusterID:option131">
                        <value>E12 (Nguale/Nguale Sede)</value>
                    </text>
                    <text id="/data/c_ClusterID/A5:label">
                        <value>A5 (Guebuza)</value>
                    </text>
                    <text id="/data/c_ClusterID:option137">
                        <value>E18 (Tengua-Sede)</value>
                    </text>
                    <text id="/data/c_ClusterID:option136">
                        <value>E17 (Tengondiguere/Chingoma)</value>
                    </text>
                    <text id="/data/c_ClusterID/G6:label">
                        <value>G6 (Eduardo Mondlane)</value>
                    </text>
                    <text id="/data/c_ClusterID:option134">
                        <value>E15 (Tengondiguere)</value>
                    </text>
                    <text id="/data/c_ClusterID/A19:label">
                        <value>A19 (Unidade 3)</value>
                    </text>
                    <text id="/data/c_ClusterID/E300:label">
                        <value>E300 (Primeria linha de villarejo)</value>
                    </text>
                    <text id="/data/c_ClusterID/A14:label">
                        <value>A14 (Quarteirão 2)</value>
                    </text>
                    <text id="/data/c_ClusterID/E16:label">
                        <value>E16 (Tengondiguere/Bororo)</value>
                    </text>
                    <text id="/data/c_ClusterID/F16:label">
                        <value>F16 (Nhacondiua)</value>
                    </text>
                    <text id="/data/c_ClusterID/F5:label">
                        <value>F5 (Cimento)</value>
                    </text>
                    <text id="/data/c_ClusterID/B11:label">
                        <value>B11 (Meluluca-Sede)</value>
                    </text>
                    <text id="/data/c_ClusterID/B3:label">
                        <value>B3 (Chigoma)</value>
                    </text>
                    <text id="/data/c_DistrictID:label">
                        <value>Seleccione o nome do distrito</value>
                    </text>
                    <text id="/data/c_ClusterID/F19:label">
                        <value>F19 (Raposo)</value>
                    </text>
                    <text id="/data/c_ClusterID/C500:label">
                        <value>C500 (Primeria linha de villarejo)</value>
                    </text>
                    <text id="/data/c_ClusterID/A100:label">
                        <value>A100 (Primeria linha de villarejo)</value>
                    </text>
                    <text id="/data/c_DistrictID/Milange:label">
                        <value>Milange</value>
                    </text>
                    <text id="/data/c_ClusterID/SP500:label">
                        <value>SP500 (Primeria linha de villarejo)</value>
                    </text>
                    <text id="/data/c_ClusterID/D10:label">
                        <value>D10 (Mucuna)</value>
                    </text>
                    <text id="/data/c_DistrictID/Lago:label">
                        <value>Lago</value>
                    </text>
                    <text id="/data/c_ClusterID/B12:label">
                        <value>B12 (Messumba-Sede)</value>
                    </text>
                    <text id="/data/c_ClusterID/G400:label">
                        <value>G400 (Primeria linha de villarejo)</value>
                    </text>
                    <text id="/data/c_ClusterID/D5:label">
                        <value>D5 (Jassamire)</value>
                    </text>
                    <text id="/data/c_ClusterID/E10:label">
                        <value>E10 (Namurrobua)</value>
                    </text>
                    <text id="/data/c_DistrictID/Outro distrito:label">
                        <value>Outro distrito</value>
                    </text>
                    <text id="/data/c_ClusterID/B8:label">
                        <value>B8 (Mazogo Issa)</value>
                    </text>
                    <text id="/data/c_ClusterID/B17:label">
                        <value>B17 (Nkholongue)</value>
                    </text>
                    <text id="/data/c_ClusterID/B7:label">
                        <value>B7 (Lutombochi)</value>
                    </text>
                    <text id="/data/c_ClusterID:option159">
                        <value>F20 (Suze-Sede/JO)</value>
                    </text>
                    <text id="/data/c_ClusterID/C14:label">
                        <value>C14 (Mpandadzi)</value>
                    </text>
                    <text id="/data/c_ClusterID:option157">
                        <value>F18 (Pringo)</value>
                    </text>
                    <text id="/data/c_ClusterID/G3:label">
                        <value>G3 (Caia)</value>
                    </text>
                    <text id="/data/c_ClusterID:option151">
                        <value>F12 (Muandje)</value>
                    </text>
                    <text id="/data/c_ClusterID/A500:label">
                        <value>A500 (Primeria linha de villarejo)</value>
                    </text>
                    <text id="/data/c_ClusterID/C400:label">
                        <value>C400 (Primeria linha de villarejo)</value>
                    </text>
                    <text id="/data/c_ClusterID/G19:label">
                        <value>G19 (Nsoca)</value>
                    </text>
                    <text id="/data/c_ClusterID/E14:label">
                        <value>E14 (Nkango)</value>
                    </text>
                    <text id="/data/c_ClusterID:option142">
                        <value>F3 (Caixote)</value>
                    </text>
                    <text id="/data/c_ClusterID:option143">
                        <value>F4 (Calula)</value>
                    </text>
                    <text id="/data/c_ClusterID:option140">
                        <value>F1 (Alfazema)</value>
                    </text>
                    <text id="/data/c_ClusterID:label">
                        <value>Insira a identificação do grupo</value>
                    </text>
                    <text id="/data/c_ClusterID:option146">
                        <value>F7 (Magamba)</value>
                    </text>
                    <text id="/data/c_ClusterID:option147">
                        <value>F8 (Majane)</value>
                    </text>
                    <text id="/data/c_ClusterID:option144">
                        <value>F5 (Cimento)</value>
                    </text>
                    <text id="/data/c_ClusterID/C100:label">
                        <value>C100 (Primeria linha de villarejo)</value>
                    </text>
                    <text id="/data/c_ClusterID:option148">
                        <value>F9 (Manso-Sede)</value>
                    </text>
                    <text id="/data/c_ClusterID:option149">
                        <value>F10 (Marrundo)</value>
                    </text>
                    <text id="/data/c_ClusterID/A2:label">
                        <value>A2 (7 de Setembro)</value>
                    </text>
                    <text id="/data/c_ClusterID/D1:label">
                        <value>D1 (Carerequene)</value>
                    </text>
                    <text id="/data/c_ClusterID/B200:label">
                        <value>B200 (Primeria linha de villarejo)</value>
                    </text>
                    <text id="/data/c_ClusterID:option165">
                        <value>G6 (Eduardo Mondlane)</value>
                    </text>
                    <text id="/data/c_ClusterID/G1:label">
                        <value>G1 (Antigos Combatentes)</value>
                    </text>
                    <text id="/data/c_ClusterID:option50">
                        <value>A11 (Nhanchenje)</value>
                    </text>
                    <text id="/data/c_ClusterID:option53">
                        <value>A14 (Quarteirão 2)</value>
                    </text>
                    <text id="/data/c_ClusterID:option33">
                        <value>G400 (Primeria linha de villarejo)</value>
                    </text>
                    <text id="/data/c_ClusterID/C17:label">
                        <value>C17 (Nkhamba 2)</value>
                    </text>
                    <text id="/data/c_ClusterID:option31">
                        <value>G200 (Primeria linha de villarejo)</value>
                    </text>
                    <text id="/data/c_ClusterID:option30">
                        <value>G100 (Primeria linha de villarejo)</value>
                    </text>
                    <text id="/data/c_ClusterID:option37">
                        <value>SP300 (Primeria linha de villarejo)</value>
                    </text>
                    <text id="/data/c_ClusterID:option36">
                        <value>SP200 (Primeria linha de villarejo)</value>
                    </text>
                    <text id="/data/c_ClusterID:option35">
                        <value>SP100 (Primeria linha de villarejo)</value>
                    </text>
                    <text id="/data/c_ClusterID:option34">
                        <value>G500 (Primeria linha de villarejo)</value>
                    </text>
                    <text id="/data/c_ClusterID:option39">
                        <value>SP500 (Primeria linha de villarejo)</value>
                    </text>
                    <text id="/data/c_ClusterID:option38">
                        <value>SP400 (Primeria linha de villarejo)</value>
                    </text>
                    <text id="/data/c_ClusterID/A20:label">
                        <value>A20 (Unidade 73)</value>
                    </text>
                    <text id="/data/c_ClusterID:option46">
                        <value>A7 (Josina Machel)</value>
                    </text>
                    <text id="/data/c_ClusterID:option47">
                        <value>A8 (Josina Machel)</value>
                    </text>
                    <text id="/data/c_ClusterID:option44">
                        <value>A5 (Guebuza)</value>
                    </text>
                    <text id="/data/c_ClusterID:option45">
                        <value>A6 (Joaquim Chissano)</value>
                    </text>
                    <text id="/data/c_ClusterID:option42">
                        <value>A3 (Cahoue)</value>
                    </text>
                    <text id="/data/c_ClusterID:option43">
                        <value>A4 (Cawawa)</value>
                    </text>
                    <text id="/data/c_ClusterID:option40">
                        <value>A1 (4 de Outubro)</value>
                    </text>
                    <text id="/data/c_ClusterID:option41">
                        <value>A2 (7 de Setembro)</value>
                    </text>
                    <text id="/data/c_ClusterID:option48">
                        <value>A9 (Josina Machel)</value>
                    </text>
                    <text id="/data/c_ClusterID:option49">
                        <value>A10 (Nhamidzi-Sede)</value>
                    </text>
                    <text id="/data/c_ClusterID/E9:label">
                        <value>E9 (Nampinga)</value>
                    </text>
                    <text id="/data/c_ClusterID:option10">
                        <value>C100 (Primeria linha de villarejo)</value>
                    </text>
                    <text id="/data/c_ClusterID/C4:label">
                        <value>C4 (Cachere-Sede)</value>
                    </text>
                    <text id="/data/c_ClusterID/F4:label">
                        <value>F4 (Calula)</value>
                    </text>
                    <text id="/data/c_ClusterID/D300:label">
                        <value>D300 (Primeria linha de villarejo)</value>
                    </text>
                    <text id="/data/c_ClusterID/B2:label">
                        <value>B2 (Chidjidji)</value>
                    </text>
                    <text id="/data/c_ClusterID/B4:label">
                        <value>B4 (Junta 1)</value>
                    </text>
                    <text id="/data/c_ClusterID/A13:label">
                        <value>A13 (Quarteirão 1)</value>
                    </text>
                    <text id="/data/c_ClusterID:option106">
                        <value>D7 (Maunda)</value>
                    </text>
                    <text id="/data/c_ClusterID:option107">
                        <value>D8 (Mepunga)</value>
                    </text>
                    <text id="/data/c_ClusterID:option104">
                        <value>D5 (Jassamire)</value>
                    </text>
                    <text id="/data/c_ClusterID:option105">
                        <value>D6 (Manhungua)</value>
                    </text>
                    <text id="/data/c_ClusterID:option102">
                        <value>D3 (Cuvinhe)</value>
                    </text>
                    <text id="/data/c_ClusterID:option103">
                        <value>D4 (Insaca-Sede)</value>
                    </text>
                    <text id="/data/c_ClusterID:option100">
                        <value>D1 (Carerequene)</value>
                    </text>
                    <text id="/data/c_ClusterID:option101">
                        <value>D2 (Chitimbe)</value>
                    </text>
                    <text id="/data/c_ClusterID/SP400:label">
                        <value>SP400 (Primeria linha de villarejo)</value>
                    </text>
                    <text id="/data/c_ClusterID:option108">
                        <value>D9 (Muanheue)</value>
                    </text>
                    <text id="/data/c_ClusterID:option109">
                        <value>D10 (Mucuna)</value>
                    </text>
                    <text id="/data/c_ClusterID/C6:label">
                        <value>C6 (Chingambwa)</value>
                    </text>
                    <text id="/data/c_ClusterID/G7:label">
                        <value>G7 (Hwombe)</value>
                    </text>
                    <text id="/data/c_ClusterID/G5:label">
                        <value>G5 (Chilapitangongo)</value>
                    </text>
                    <text id="/data/c_ClusterID/B400:label">
                        <value>B400 (Primeria linha de villarejo)</value>
                    </text>
                    <text id="/data/c_ClusterID/E20:label">
                        <value>E20 (Wilsone-Sede)</value>
                    </text>
                    <text id="/data/c_ClusterID/F300:label">
                        <value>F300 (Primeria linha de villarejo)</value>
                    </text>
                    <text id="/data/c_ClusterID/D4:label">
                        <value>D4 (Insaca-Sede)</value>
                    </text>
                    <text id="/data/c_ClusterID/E12:label">
                        <value>E12 (Nguale/Nguale Sede)</value>
                    </text>
                    <text id="/data/c_ClusterID:option1">
                        <value>A200 (Primeria linha de villarejo)</value>
                    </text>
                    <text id="/data/c_ClusterID:option0">
                        <value>A100 (Primeria linha de villarejo)</value>
                    </text>
                    <text id="/data/c_ClusterID:option3">
                        <value>A400 (Primeria linha de villarejo)</value>
                    </text>
                    <text id="/data/c_ClusterID:option2">
                        <value>A300 (Primeria linha de villarejo)</value>
                    </text>
                    <text id="/data/c_ClusterID:option5">
                        <value>B500 (Primeria linha de villarejo)</value>
                    </text>
                    <text id="/data/c_ClusterID:option4">
                        <value>A500 (Primeria linha de villarejo)</value>
                    </text>
                    <text id="/data/c_ClusterID:option7">
                        <value>B200 (Primeria linha de villarejo)</value>
                    </text>
                    <text id="/data/c_ClusterID:option6">
                        <value>B100 (Primeria linha de villarejo)</value>
                    </text>
                    <text id="/data/c_ClusterID:option9">
                        <value>B400 (Primeria linha de villarejo)</value>
                    </text>
                    <text id="/data/c_ClusterID:option8">
                        <value>B300 (Primeria linha de villarejo)</value>
                    </text>
                    <text id="/data/c_ClusterID/E4:label">
                        <value>E4 (Gurai)</value>
                    </text>
                    <text id="/data/c_ClusterID/B300:label">
                        <value>B300 (Primeria linha de villarejo)</value>
                    </text>
                    <text id="/data/c_ClusterID/E7:label">
                        <value>E7 (Mosquito)</value>
                    </text>
                    <text id="/data/c_ClusterID/E6:label">
                        <value>E6 (Licuide)</value>
                    </text>
                    <text id="/data/c_ClusterID/D8:label">
                        <value>D8 (Mepunga)</value>
                    </text>
                    <text id="/data/c_ClusterID/B16:label">
                        <value>B16 (Nguimbi)</value>
                    </text>
                    <text id="/data/c_ClusterID/D13:label">
                        <value>D13 (Muhomua)</value>
                    </text>
                    <text id="/data/c_ClusterID/D16:label">
                        <value>D16 (Nancuenha)</value>
                    </text>
                    <text id="/data/c_ClusterID/E18:label">
                        <value>E18 (Tengua-Sede)</value>
                    </text>
                    <text id="/data/c_ClusterID/A200:label">
                        <value>A200 (Primeria linha de villarejo)</value>
                    </text>
                    <text id="/data/c_ClusterID/B6:label">
                        <value>B6 (Liona)</value>
                    </text>
                    <text id="/data/c_ClusterID/SP300:label">
                        <value>SP300 (Primeria linha de villarejo)</value>
                    </text>
                    <text id="/data/c_ClusterID:option79">
                        <value>B20 (Tulo Cambona)</value>
                    </text>
                    <text id="/data/c_ClusterID:option78">
                        <value>B19 (Ntumba)</value>
                    </text>
                    <text id="/data/c_ClusterID:option77">
                        <value>B18 (N'Nane)</value>
                    </text>
                    <text id="/data/c_ClusterID:option76">
                        <value>B17 (Nkholongue)</value>
                    </text>
                    <text id="/data/c_ClusterID:option75">
                        <value>B16 (Nguimbi)</value>
                    </text>
                    <text id="/data/c_ClusterID:option74">
                        <value>B15 (Ncape)</value>
                    </text>
                    <text id="/data/c_ClusterID:option73">
                        <value>B14 (Mitondo)</value>
                    </text>
                    <text id="/data/c_ClusterID:option72">
                        <value>B13 (Micucué)</value>
                    </text>
                    <text id="/data/c_ClusterID:option71">
                        <value>B12 (Messumba-Sede)</value>
                    </text>
                    <text id="/data/c_ClusterID:option70">
                        <value>B11 (Meluluca-Sede)</value>
                    </text>
                    <text id="/data/c_ClusterID/F8:label">
                        <value>F8 (Majane)</value>
                    </text>
                    <text id="/data/c_ClusterID/G12:label">
                        <value>G12 (Maundjidi)</value>
                    </text>
                    <text id="/data/c_ClusterID:option88">
                        <value>C9 (Kamwankhuko)</value>
                    </text>
                    <text id="/data/c_ClusterID/G17:label">
                        <value>G17 (Nhamuedje)</value>
                    </text>
                    <text id="/data/c_ClusterID/C200:label">
                        <value>C200 (Primeria linha de villarejo)</value>
                    </text>
                    <text id="/data/c_ClusterID/G9:label">
                        <value>G9 (Macaloge-Sede)</value>
                    </text>
                    <text id="/data/c_ClusterID/C15:label">
                        <value>C15 (Mukanga)</value>
                    </text>
                    <text id="/data/c_ClusterID/A12:label">
                        <value>A12 (Quarteirao 1)</value>
                    </text>
                    <text id="/data/c_ClusterID/E13:label">
                        <value>E13 (Nguale/Podogoma)</value>
                    </text>
                    <text id="/data/c_ClusterID/D11:label">
                        <value>D11 (Muecua)</value>
                    </text>
                    <text id="/data/c_ClusterID:option158">
                        <value>F19 (Raposo)</value>
                    </text>
                    <text id="/data/c_ClusterID:option155">
                        <value>F16 (Nhacondiua)</value>
                    </text>
                    <text id="/data/c_ClusterID:option154">
                        <value>F15 (Nangir)</value>
                    </text>
                    <text id="/data/c_ClusterID/G2:label">
                        <value>G2 (Bagarila)</value>
                    </text>
                    <text id="/data/c_ClusterID:option156">
                        <value>F17 (Nharine)</value>
                    </text>
                    <text id="/data/c_ClusterID/C16:label">
                        <value>C16 (Nhamalemba)</value>
                    </text>
                    <text id="/data/c_ClusterID:option150">
                        <value>F11 (Muandiua-Sede)</value>
                    </text>
                    <text id="/data/c_ClusterID:option153">
                        <value>F14 (Namaunde)</value>
                    </text>
                    <text id="/data/c_ClusterID:option152">
                        <value>F13 (Namachila)</value>
                    </text>
                    <text id="/data/c_ClusterID/G10:label">
                        <value>G10 (Malemia)</value>
                    </text>
                    <text id="/data/c_ClusterID/F500:label">
                        <value>F500 (Primeria linha de villarejo)</value>
                    </text>
                    <text id="/data/c_ClusterID/C18:label">
                        <value>C18 (Nteme/Nhanseula)</value>
                    </text>
                    <text id="/data/c_ClusterID/A11:label">
                        <value>A11 (Nhanchenje)</value>
                    </text>
                    <text id="/data/c_DistrictID/Mecanhelas:label">
                        <value>Mecanhelas</value>
                    </text>

        </translation>
      </itext>

<instance id="districts">
  <root>
    <item>
      <itextId>/data/c_DistrictID:option0</itextId>
      <name>Cahora-Bassa</name>
    </item>
    <item>
      <itextId>/data/c_DistrictID:option1</itextId>
      <name>Lago</name>
    </item>
    <item>
      <itextId>/data/c_DistrictID:option2</itextId>
      <name>Maravia</name>
    </item>
    <item>
      <itextId>/data/c_DistrictID:option3</itextId>
      <name>Mecanhelas</name>
    </item>
    <item>
      <itextId>/data/c_DistrictID:option4</itextId>
      <name>Milange</name>
    </item>
    <item>
      <itextId>/data/c_DistrictID:option5</itextId>
      <name>Morrumbala</name>
    </item>
    <item>
      <itextId>/data/c_DistrictID:option6</itextId>
      <name>Sanga</name>
    </item>
    <item>
      <itextId>/data/c_DistrictID:option7</itextId>
      <name>Outro distrito</name>
    </item>
  </root>
</instance>
<instance id="clusters">
  <root>
    <item>
      <itextId>/data/c_ClusterID:option0</itextId>
      <c_DistrictID>Cahora-Bassa</c_DistrictID>
      <name>A100</name>
    </item>
    <item>
      <itextId>/data/c_ClusterID:option1</itextId>
      <c_DistrictID>Cahora-Bassa</c_DistrictID>
      <name>A200</name>
    </item>
    <item>
      <itextId>/data/c_ClusterID:option2</itextId>
      <c_DistrictID>Cahora-Bassa</c_DistrictID>
      <name>A300</name>
    </item>
    <item>
      <itextId>/data/c_ClusterID:option3</itextId>
      <c_DistrictID>Cahora-Bassa</c_DistrictID>
      <name>A400</name>
    </item>
    <item>
      <itextId>/data/c_ClusterID:option4</itextId>
      <c_DistrictID>Cahora-Bassa</c_DistrictID>
      <name>A500</name>
    </item>
    <item>
      <itextId>/data/c_ClusterID:option5</itextId>
      <c_DistrictID>Lago</c_DistrictID>
      <name>B500</name>
    </item>
    <item>
      <itextId>/data/c_ClusterID:option6</itextId>
      <c_DistrictID>Lago</c_DistrictID>
      <name>B100</name>
    </item>
    <item>
      <itextId>/data/c_ClusterID:option7</itextId>
      <c_DistrictID>Lago</c_DistrictID>
      <name>B200</name>
    </item>
    <item>
      <itextId>/data/c_ClusterID:option8</itextId>
      <c_DistrictID>Lago</c_DistrictID>
      <name>B300</name>
    </item>
    <item>
      <itextId>/data/c_ClusterID:option9</itextId>
      <c_DistrictID>Lago</c_DistrictID>
      <name>B400</name>
    </item>
    <item>
      <itextId>/data/c_ClusterID:option10</itextId>
      <c_DistrictID>Maravia</c_DistrictID>
      <name>C100</name>
    </item>
    <item>
      <itextId>/data/c_ClusterID:option11</itextId>
      <c_DistrictID>Maravia</c_DistrictID>
      <name>C200</name>
    </item>
    <item>
      <itextId>/data/c_ClusterID:option12</itextId>
      <c_DistrictID>Maravia</c_DistrictID>
      <name>C300</name>
    </item>
    <item>
      <itextId>/data/c_ClusterID:option13</itextId>
      <c_DistrictID>Maravia</c_DistrictID>
      <name>C400</name>
    </item>
    <item>
      <itextId>/data/c_ClusterID:option14</itextId>
      <c_DistrictID>Maravia</c_DistrictID>
      <name>C500</name>
    </item>
    <item>
      <itextId>/data/c_ClusterID:option15</itextId>
      <c_DistrictID>Mecanhelas</c_DistrictID>
      <name>D100</name>
    </item>
    <item>
      <itextId>/data/c_ClusterID:option16</itextId>
      <c_DistrictID>Mecanhelas</c_DistrictID>
      <name>D200</name>
    </item>
    <item>
      <itextId>/data/c_ClusterID:option17</itextId>
      <c_DistrictID>Mecanhelas</c_DistrictID>
      <name>D300</name>
    </item>
    <item>
      <itextId>/data/c_ClusterID:option18</itextId>
      <c_DistrictID>Mecanhelas</c_DistrictID>
      <name>D400</name>
    </item>
    <item>
      <itextId>/data/c_ClusterID:option19</itextId>
      <c_DistrictID>Mecanhelas</c_DistrictID>
      <name>D500</name>
    </item>
    <item>
      <itextId>/data/c_ClusterID:option20</itextId>
      <c_DistrictID>Milange</c_DistrictID>
      <name>E100</name>
    </item>
    <item>
      <itextId>/data/c_ClusterID:option21</itextId>
      <c_DistrictID>Milange</c_DistrictID>
      <name>E200</name>
    </item>
    <item>
      <itextId>/data/c_ClusterID:option22</itextId>
      <c_DistrictID>Milange</c_DistrictID>
      <name>E300</name>
    </item>
    <item>
      <itextId>/data/c_ClusterID:option23</itextId>
      <c_DistrictID>Milange</c_DistrictID>
      <name>E400</name>
    </item>
    <item>
      <itextId>/data/c_ClusterID:option24</itextId>
      <c_DistrictID>Milange</c_DistrictID>
      <name>E500</name>
    </item>
    <item>
      <itextId>/data/c_ClusterID:option25</itextId>
      <c_DistrictID>Morrumbala</c_DistrictID>
      <name>F100</name>
    </item>
    <item>
      <itextId>/data/c_ClusterID:option26</itextId>
      <c_DistrictID>Morrumbala</c_DistrictID>
      <name>F200</name>
    </item>
    <item>
      <itextId>/data/c_ClusterID:option27</itextId>
      <c_DistrictID>Morrumbala</c_DistrictID>
      <name>F300</name>
    </item>
    <item>
      <itextId>/data/c_ClusterID:option28</itextId>
      <c_DistrictID>Morrumbala</c_DistrictID>
      <name>F400</name>
    </item>
    <item>
      <itextId>/data/c_ClusterID:option29</itextId>
      <c_DistrictID>Morrumbala</c_DistrictID>
      <name>F500</name>
    </item>
    <item>
      <itextId>/data/c_ClusterID:option30</itextId>
      <c_DistrictID>Sanga</c_DistrictID>
      <name>G100</name>
    </item>
    <item>
      <itextId>/data/c_ClusterID:option31</itextId>
      <c_DistrictID>Sanga</c_DistrictID>
      <name>G200</name>
    </item>
    <item>
      <itextId>/data/c_ClusterID:option32</itextId>
      <c_DistrictID>Sanga</c_DistrictID>
      <name>G300</name>
    </item>
    <item>
      <itextId>/data/c_ClusterID:option33</itextId>
      <c_DistrictID>Sanga</c_DistrictID>
      <name>G400</name>
    </item>
    <item>
      <itextId>/data/c_ClusterID:option34</itextId>
      <c_DistrictID>Sanga</c_DistrictID>
      <name>G500</name>
    </item>
    <item>
      <itextId>/data/c_ClusterID:option35</itextId>
      <c_DistrictID>Outro distrito</c_DistrictID>
      <name>SP100</name>
    </item>
    <item>
      <itextId>/data/c_ClusterID:option36</itextId>
      <c_DistrictID>Outro distrito</c_DistrictID>
      <name>SP200</name>
    </item>
    <item>
      <itextId>/data/c_ClusterID:option37</itextId>
      <c_DistrictID>Outro distrito</c_DistrictID>
      <name>SP300</name>
    </item>
    <item>
      <itextId>/data/c_ClusterID:option38</itextId>
      <c_DistrictID>Outro distrito</c_DistrictID>
      <name>SP400</name>
    </item>
    <item>
      <itextId>/data/c_ClusterID:option39</itextId>
      <c_DistrictID>Outro distrito</c_DistrictID>
      <name>SP500</name>
    </item>
    <item>
      <itextId>/data/c_ClusterID:option40</itextId>
      <c_DistrictID>Cahora-Bassa</c_DistrictID>
      <name>A1</name>
    </item>
    <item>
      <itextId>/data/c_ClusterID:option41</itextId>
      <c_DistrictID>Cahora-Bassa</c_DistrictID>
      <name>A2</name>
    </item>
    <item>
      <itextId>/data/c_ClusterID:option42</itextId>
      <c_DistrictID>Cahora-Bassa</c_DistrictID>
      <name>A3</name>
    </item>
    <item>
      <itextId>/data/c_ClusterID:option43</itextId>
      <c_DistrictID>Cahora-Bassa</c_DistrictID>
      <name>A4</name>
    </item>
    <item>
      <itextId>/data/c_ClusterID:option44</itextId>
      <c_DistrictID>Cahora-Bassa</c_DistrictID>
      <name>A5</name>
    </item>
    <item>
      <itextId>/data/c_ClusterID:option45</itextId>
      <c_DistrictID>Cahora-Bassa</c_DistrictID>
      <name>A6</name>
    </item>
    <item>
      <itextId>/data/c_ClusterID:option46</itextId>
      <c_DistrictID>Cahora-Bassa</c_DistrictID>
      <name>A7</name>
    </item>
    <item>
      <itextId>/data/c_ClusterID:option47</itextId>
      <c_DistrictID>Cahora-Bassa</c_DistrictID>
      <name>A8</name>
    </item>
    <item>
      <itextId>/data/c_ClusterID:option48</itextId>
      <c_DistrictID>Cahora-Bassa</c_DistrictID>
      <name>A9</name>
    </item>
    <item>
      <itextId>/data/c_ClusterID:option49</itextId>
      <c_DistrictID>Cahora-Bassa</c_DistrictID>
      <name>A10</name>
    </item>
    <item>
      <itextId>/data/c_ClusterID:option50</itextId>
      <c_DistrictID>Cahora-Bassa</c_DistrictID>
      <name>A11</name>
    </item>
    <item>
      <itextId>/data/c_ClusterID:option51</itextId>
      <c_DistrictID>Cahora-Bassa</c_DistrictID>
      <name>A12</name>
    </item>
    <item>
      <itextId>/data/c_ClusterID:option52</itextId>
      <c_DistrictID>Cahora-Bassa</c_DistrictID>
      <name>A13</name>
    </item>
    <item>
      <itextId>/data/c_ClusterID:option53</itextId>
      <c_DistrictID>Cahora-Bassa</c_DistrictID>
      <name>A14</name>
    </item>
    <item>
      <itextId>/data/c_ClusterID:option54</itextId>
      <c_DistrictID>Cahora-Bassa</c_DistrictID>
      <name>A15</name>
    </item>
    <item>
      <itextId>/data/c_ClusterID:option55</itextId>
      <c_DistrictID>Cahora-Bassa</c_DistrictID>
      <name>A16</name>
    </item>
    <item>
      <itextId>/data/c_ClusterID:option56</itextId>
      <c_DistrictID>Cahora-Bassa</c_DistrictID>
      <name>A17</name>
    </item>
    <item>
      <itextId>/data/c_ClusterID:option57</itextId>
      <c_DistrictID>Cahora-Bassa</c_DistrictID>
      <name>A18</name>
    </item>
    <item>
      <itextId>/data/c_ClusterID:option58</itextId>
      <c_DistrictID>Cahora-Bassa</c_DistrictID>
      <name>A19</name>
    </item>
    <item>
      <itextId>/data/c_ClusterID:option59</itextId>
      <c_DistrictID>Cahora-Bassa</c_DistrictID>
      <name>A20</name>
    </item>
    <item>
      <itextId>/data/c_ClusterID:option60</itextId>
      <c_DistrictID>Lago</c_DistrictID>
      <name>B1</name>
    </item>
    <item>
      <itextId>/data/c_ClusterID:option61</itextId>
      <c_DistrictID>Lago</c_DistrictID>
      <name>B2</name>
    </item>
    <item>
      <itextId>/data/c_ClusterID:option62</itextId>
      <c_DistrictID>Lago</c_DistrictID>
      <name>B3</name>
    </item>
    <item>
      <itextId>/data/c_ClusterID:option63</itextId>
      <c_DistrictID>Lago</c_DistrictID>
      <name>B4</name>
    </item>
    <item>
      <itextId>/data/c_ClusterID:option64</itextId>
      <c_DistrictID>Lago</c_DistrictID>
      <name>B5</name>
    </item>
    <item>
      <itextId>/data/c_ClusterID:option65</itextId>
      <c_DistrictID>Lago</c_DistrictID>
      <name>B6</name>
    </item>
    <item>
      <itextId>/data/c_ClusterID:option66</itextId>
      <c_DistrictID>Lago</c_DistrictID>
      <name>B7</name>
    </item>
    <item>
      <itextId>/data/c_ClusterID:option67</itextId>
      <c_DistrictID>Lago</c_DistrictID>
      <name>B8</name>
    </item>
    <item>
      <itextId>/data/c_ClusterID:option68</itextId>
      <c_DistrictID>Lago</c_DistrictID>
      <name>B9</name>
    </item>
    <item>
      <itextId>/data/c_ClusterID:option69</itextId>
      <c_DistrictID>Lago</c_DistrictID>
      <name>B10</name>
    </item>
    <item>
      <itextId>/data/c_ClusterID:option70</itextId>
      <c_DistrictID>Lago</c_DistrictID>
      <name>B11</name>
    </item>
    <item>
      <itextId>/data/c_ClusterID:option71</itextId>
      <c_DistrictID>Lago</c_DistrictID>
      <name>B12</name>
    </item>
    <item>
      <itextId>/data/c_ClusterID:option72</itextId>
      <c_DistrictID>Lago</c_DistrictID>
      <name>B13</name>
    </item>
    <item>
      <itextId>/data/c_ClusterID:option73</itextId>
      <c_DistrictID>Lago</c_DistrictID>
      <name>B14</name>
    </item>
    <item>
      <itextId>/data/c_ClusterID:option74</itextId>
      <c_DistrictID>Lago</c_DistrictID>
      <name>B15</name>
    </item>
    <item>
      <itextId>/data/c_ClusterID:option75</itextId>
      <c_DistrictID>Lago</c_DistrictID>
      <name>B16</name>
    </item>
    <item>
      <itextId>/data/c_ClusterID:option76</itextId>
      <c_DistrictID>Lago</c_DistrictID>
      <name>B17</name>
    </item>
    <item>
      <itextId>/data/c_ClusterID:option77</itextId>
      <c_DistrictID>Lago</c_DistrictID>
      <name>B18</name>
    </item>
    <item>
      <itextId>/data/c_ClusterID:option78</itextId>
      <c_DistrictID>Lago</c_DistrictID>
      <name>B19</name>
    </item>
    <item>
      <itextId>/data/c_ClusterID:option79</itextId>
      <c_DistrictID>Lago</c_DistrictID>
      <name>B20</name>
    </item>
    <item>
      <itextId>/data/c_ClusterID:option80</itextId>
      <c_DistrictID>Maravia</c_DistrictID>
      <name>C1</name>
    </item>
    <item>
      <itextId>/data/c_ClusterID:option81</itextId>
      <c_DistrictID>Maravia</c_DistrictID>
      <name>C2</name>
    </item>
    <item>
      <itextId>/data/c_ClusterID:option82</itextId>
      <c_DistrictID>Maravia</c_DistrictID>
      <name>C3</name>
    </item>
    <item>
      <itextId>/data/c_ClusterID:option83</itextId>
      <c_DistrictID>Maravia</c_DistrictID>
      <name>C4</name>
    </item>
    <item>
      <itextId>/data/c_ClusterID:option84</itextId>
      <c_DistrictID>Maravia</c_DistrictID>
      <name>C5</name>
    </item>
    <item>
      <itextId>/data/c_ClusterID:option85</itextId>
      <c_DistrictID>Maravia</c_DistrictID>
      <name>C6</name>
    </item>
    <item>
      <itextId>/data/c_ClusterID:option86</itextId>
      <c_DistrictID>Maravia</c_DistrictID>
      <name>C7</name>
    </item>
    <item>
      <itextId>/data/c_ClusterID:option87</itextId>
      <c_DistrictID>Maravia</c_DistrictID>
      <name>C8</name>
    </item>
    <item>
      <itextId>/data/c_ClusterID:option88</itextId>
      <c_DistrictID>Maravia</c_DistrictID>
      <name>C9</name>
    </item>
    <item>
      <itextId>/data/c_ClusterID:option89</itextId>
      <c_DistrictID>Maravia</c_DistrictID>
      <name>C10</name>
    </item>
    <item>
      <itextId>/data/c_ClusterID:option90</itextId>
      <c_DistrictID>Maravia</c_DistrictID>
      <name>C11</name>
    </item>
    <item>
      <itextId>/data/c_ClusterID:option91</itextId>
      <c_DistrictID>Maravia</c_DistrictID>
      <name>C12</name>
    </item>
    <item>
      <itextId>/data/c_ClusterID:option92</itextId>
      <c_DistrictID>Maravia</c_DistrictID>
      <name>C13</name>
    </item>
    <item>
      <itextId>/data/c_ClusterID:option93</itextId>
      <c_DistrictID>Maravia</c_DistrictID>
      <name>C14</name>
    </item>
    <item>
      <itextId>/data/c_ClusterID:option94</itextId>
      <c_DistrictID>Maravia</c_DistrictID>
      <name>C15</name>
    </item>
    <item>
      <itextId>/data/c_ClusterID:option95</itextId>
      <c_DistrictID>Maravia</c_DistrictID>
      <name>C16</name>
    </item>
    <item>
      <itextId>/data/c_ClusterID:option96</itextId>
      <c_DistrictID>Maravia</c_DistrictID>
      <name>C17</name>
    </item>
    <item>
      <itextId>/data/c_ClusterID:option97</itextId>
      <c_DistrictID>Maravia</c_DistrictID>
      <name>C18</name>
    </item>
    <item>
      <itextId>/data/c_ClusterID:option98</itextId>
      <c_DistrictID>Maravia</c_DistrictID>
      <name>C19</name>
    </item>
    <item>
      <itextId>/data/c_ClusterID:option99</itextId>
      <c_DistrictID>Maravia</c_DistrictID>
      <name>C20</name>
    </item>
    <item>
      <itextId>/data/c_ClusterID:option100</itextId>
      <c_DistrictID>Mecanhelas</c_DistrictID>
      <name>D1</name>
    </item>
    <item>
      <itextId>/data/c_ClusterID:option101</itextId>
      <c_DistrictID>Mecanhelas</c_DistrictID>
      <name>D2</name>
    </item>
    <item>
      <itextId>/data/c_ClusterID:option102</itextId>
      <c_DistrictID>Mecanhelas</c_DistrictID>
      <name>D3</name>
    </item>
    <item>
      <itextId>/data/c_ClusterID:option103</itextId>
      <c_DistrictID>Mecanhelas</c_DistrictID>
      <name>D4</name>
    </item>
    <item>
      <itextId>/data/c_ClusterID:option104</itextId>
      <c_DistrictID>Mecanhelas</c_DistrictID>
      <name>D5</name>
    </item>
    <item>
      <itextId>/data/c_ClusterID:option105</itextId>
      <c_DistrictID>Mecanhelas</c_DistrictID>
      <name>D6</name>
    </item>
    <item>
      <itextId>/data/c_ClusterID:option106</itextId>
      <c_DistrictID>Mecanhelas</c_DistrictID>
      <name>D7</name>
    </item>
    <item>
      <itextId>/data/c_ClusterID:option107</itextId>
      <c_DistrictID>Mecanhelas</c_DistrictID>
      <name>D8</name>
    </item>
    <item>
      <itextId>/data/c_ClusterID:option108</itextId>
      <c_DistrictID>Mecanhelas</c_DistrictID>
      <name>D9</name>
    </item>
    <item>
      <itextId>/data/c_ClusterID:option109</itextId>
      <c_DistrictID>Mecanhelas</c_DistrictID>
      <name>D10</name>
    </item>
    <item>
      <itextId>/data/c_ClusterID:option110</itextId>
      <c_DistrictID>Mecanhelas</c_DistrictID>
      <name>D11</name>
    </item>
    <item>
      <itextId>/data/c_ClusterID:option111</itextId>
      <c_DistrictID>Mecanhelas</c_DistrictID>
      <name>D12</name>
    </item>
    <item>
      <itextId>/data/c_ClusterID:option112</itextId>
      <c_DistrictID>Mecanhelas</c_DistrictID>
      <name>D13</name>
    </item>
    <item>
      <itextId>/data/c_ClusterID:option113</itextId>
      <c_DistrictID>Mecanhelas</c_DistrictID>
      <name>D14</name>
    </item>
    <item>
      <itextId>/data/c_ClusterID:option114</itextId>
      <c_DistrictID>Mecanhelas</c_DistrictID>
      <name>D15</name>
    </item>
    <item>
      <itextId>/data/c_ClusterID:option115</itextId>
      <c_DistrictID>Mecanhelas</c_DistrictID>
      <name>D16</name>
    </item>
    <item>
      <itextId>/data/c_ClusterID:option116</itextId>
      <c_DistrictID>Mecanhelas</c_DistrictID>
      <name>D17</name>
    </item>
    <item>
      <itextId>/data/c_ClusterID:option117</itextId>
      <c_DistrictID>Mecanhelas</c_DistrictID>
      <name>D18</name>
    </item>
    <item>
      <itextId>/data/c_ClusterID:option118</itextId>
      <c_DistrictID>Mecanhelas</c_DistrictID>
      <name>D19</name>
    </item>
    <item>
      <itextId>/data/c_ClusterID:option119</itextId>
      <c_DistrictID>Mecanhelas</c_DistrictID>
      <name>D20</name>
    </item>
    <item>
      <itextId>/data/c_ClusterID:option120</itextId>
      <c_DistrictID>Milange</c_DistrictID>
      <name>E1</name>
    </item>
    <item>
      <itextId>/data/c_ClusterID:option121</itextId>
      <c_DistrictID>Milange</c_DistrictID>
      <name>E2</name>
    </item>
    <item>
      <itextId>/data/c_ClusterID:option122</itextId>
      <c_DistrictID>Milange</c_DistrictID>
      <name>E3</name>
    </item>
    <item>
      <itextId>/data/c_ClusterID:option123</itextId>
      <c_DistrictID>Milange</c_DistrictID>
      <name>E4</name>
    </item>
    <item>
      <itextId>/data/c_ClusterID:option124</itextId>
      <c_DistrictID>Milange</c_DistrictID>
      <name>E5</name>
    </item>
    <item>
      <itextId>/data/c_ClusterID:option125</itextId>
      <c_DistrictID>Milange</c_DistrictID>
      <name>E6</name>
    </item>
    <item>
      <itextId>/data/c_ClusterID:option126</itextId>
      <c_DistrictID>Milange</c_DistrictID>
      <name>E7</name>
    </item>
    <item>
      <itextId>/data/c_ClusterID:option127</itextId>
      <c_DistrictID>Milange</c_DistrictID>
      <name>E8</name>
    </item>
    <item>
      <itextId>/data/c_ClusterID:option128</itextId>
      <c_DistrictID>Milange</c_DistrictID>
      <name>E9</name>
    </item>
    <item>
      <itextId>/data/c_ClusterID:option129</itextId>
      <c_DistrictID>Milange</c_DistrictID>
      <name>E10</name>
    </item>
    <item>
      <itextId>/data/c_ClusterID:option130</itextId>
      <c_DistrictID>Milange</c_DistrictID>
      <name>E11</name>
    </item>
    <item>
      <itextId>/data/c_ClusterID:option131</itextId>
      <c_DistrictID>Milange</c_DistrictID>
      <name>E12</name>
    </item>
    <item>
      <itextId>/data/c_ClusterID:option132</itextId>
      <c_DistrictID>Milange</c_DistrictID>
      <name>E13</name>
    </item>
    <item>
      <itextId>/data/c_ClusterID:option133</itextId>
      <c_DistrictID>Milange</c_DistrictID>
      <name>E14</name>
    </item>
    <item>
      <itextId>/data/c_ClusterID:option134</itextId>
      <c_DistrictID>Milange</c_DistrictID>
      <name>E15</name>
    </item>
    <item>
      <itextId>/data/c_ClusterID:option135</itextId>
      <c_DistrictID>Milange</c_DistrictID>
      <name>E16</name>
    </item>
    <item>
      <itextId>/data/c_ClusterID:option136</itextId>
      <c_DistrictID>Milange</c_DistrictID>
      <name>E17</name>
    </item>
    <item>
      <itextId>/data/c_ClusterID:option137</itextId>
      <c_DistrictID>Milange</c_DistrictID>
      <name>E18</name>
    </item>
    <item>
      <itextId>/data/c_ClusterID:option138</itextId>
      <c_DistrictID>Milange</c_DistrictID>
      <name>E19</name>
    </item>
    <item>
      <itextId>/data/c_ClusterID:option139</itextId>
      <c_DistrictID>Milange</c_DistrictID>
      <name>E20</name>
    </item>
    <item>
      <itextId>/data/c_ClusterID:option140</itextId>
      <c_DistrictID>Morrumbala</c_DistrictID>
      <name>F1</name>
    </item>
    <item>
      <itextId>/data/c_ClusterID:option141</itextId>
      <c_DistrictID>Morrumbala</c_DistrictID>
      <name>F2</name>
    </item>
    <item>
      <itextId>/data/c_ClusterID:option142</itextId>
      <c_DistrictID>Morrumbala</c_DistrictID>
      <name>F3</name>
    </item>
    <item>
      <itextId>/data/c_ClusterID:option143</itextId>
      <c_DistrictID>Morrumbala</c_DistrictID>
      <name>F4</name>
    </item>
    <item>
      <itextId>/data/c_ClusterID:option144</itextId>
      <c_DistrictID>Morrumbala</c_DistrictID>
      <name>F5</name>
    </item>
    <item>
      <itextId>/data/c_ClusterID:option145</itextId>
      <c_DistrictID>Morrumbala</c_DistrictID>
      <name>F6</name>
    </item>
    <item>
      <itextId>/data/c_ClusterID:option146</itextId>
      <c_DistrictID>Morrumbala</c_DistrictID>
      <name>F7</name>
    </item>
    <item>
      <itextId>/data/c_ClusterID:option147</itextId>
      <c_DistrictID>Morrumbala</c_DistrictID>
      <name>F8</name>
    </item>
    <item>
      <itextId>/data/c_ClusterID:option148</itextId>
      <c_DistrictID>Morrumbala</c_DistrictID>
      <name>F9</name>
    </item>
    <item>
      <itextId>/data/c_ClusterID:option149</itextId>
      <c_DistrictID>Morrumbala</c_DistrictID>
      <name>F10</name>
    </item>
    <item>
      <itextId>/data/c_ClusterID:option150</itextId>
      <c_DistrictID>Morrumbala</c_DistrictID>
      <name>F11</name>
    </item>
    <item>
      <itextId>/data/c_ClusterID:option151</itextId>
      <c_DistrictID>Morrumbala</c_DistrictID>
      <name>F12</name>
    </item>
    <item>
      <itextId>/data/c_ClusterID:option152</itextId>
      <c_DistrictID>Morrumbala</c_DistrictID>
      <name>F13</name>
    </item>
    <item>
      <itextId>/data/c_ClusterID:option153</itextId>
      <c_DistrictID>Morrumbala</c_DistrictID>
      <name>F14</name>
    </item>
    <item>
      <itextId>/data/c_ClusterID:option154</itextId>
      <c_DistrictID>Morrumbala</c_DistrictID>
      <name>F15</name>
    </item>
    <item>
      <itextId>/data/c_ClusterID:option155</itextId>
      <c_DistrictID>Morrumbala</c_DistrictID>
      <name>F16</name>
    </item>
    <item>
      <itextId>/data/c_ClusterID:option156</itextId>
      <c_DistrictID>Morrumbala</c_DistrictID>
      <name>F17</name>
    </item>
    <item>
      <itextId>/data/c_ClusterID:option157</itextId>
      <c_DistrictID>Morrumbala</c_DistrictID>
      <name>F18</name>
    </item>
    <item>
      <itextId>/data/c_ClusterID:option158</itextId>
      <c_DistrictID>Morrumbala</c_DistrictID>
      <name>F19</name>
    </item>
    <item>
      <itextId>/data/c_ClusterID:option159</itextId>
      <c_DistrictID>Morrumbala</c_DistrictID>
      <name>F20</name>
    </item>
    <item>
      <itextId>/data/c_ClusterID:option160</itextId>
      <c_DistrictID>Sanga</c_DistrictID>
      <name>G1</name>
    </item>
    <item>
      <itextId>/data/c_ClusterID:option161</itextId>
      <c_DistrictID>Sanga</c_DistrictID>
      <name>G2</name>
    </item>
    <item>
      <itextId>/data/c_ClusterID:option162</itextId>
      <c_DistrictID>Sanga</c_DistrictID>
      <name>G3</name>
    </item>
    <item>
      <itextId>/data/c_ClusterID:option163</itextId>
      <c_DistrictID>Sanga</c_DistrictID>
      <name>G4</name>
    </item>
    <item>
      <itextId>/data/c_ClusterID:option164</itextId>
      <c_DistrictID>Sanga</c_DistrictID>
      <name>G5</name>
    </item>
    <item>
      <itextId>/data/c_ClusterID:option165</itextId>
      <c_DistrictID>Sanga</c_DistrictID>
      <name>G6</name>
    </item>
    <item>
      <itextId>/data/c_ClusterID:option166</itextId>
      <c_DistrictID>Sanga</c_DistrictID>
      <name>G7</name>
    </item>
    <item>
      <itextId>/data/c_ClusterID:option167</itextId>
      <c_DistrictID>Sanga</c_DistrictID>
      <name>G8</name>
    </item>
    <item>
      <itextId>/data/c_ClusterID:option168</itextId>
      <c_DistrictID>Sanga</c_DistrictID>
      <name>G9</name>
    </item>
    <item>
      <itextId>/data/c_ClusterID:option169</itextId>
      <c_DistrictID>Sanga</c_DistrictID>
      <name>G10</name>
    </item>
    <item>
      <itextId>/data/c_ClusterID:option170</itextId>
      <c_DistrictID>Sanga</c_DistrictID>
      <name>G11</name>
    </item>
    <item>
      <itextId>/data/c_ClusterID:option171</itextId>
      <c_DistrictID>Sanga</c_DistrictID>
      <name>G12</name>
    </item>
    <item>
      <itextId>/data/c_ClusterID:option172</itextId>
      <c_DistrictID>Sanga</c_DistrictID>
      <name>G13</name>
    </item>
    <item>
      <itextId>/data/c_ClusterID:option173</itextId>
      <c_DistrictID>Sanga</c_DistrictID>
      <name>G14</name>
    </item>
    <item>
      <itextId>/data/c_ClusterID:option174</itextId>
      <c_DistrictID>Sanga</c_DistrictID>
      <name>G15</name>
    </item>
    <item>
      <itextId>/data/c_ClusterID:option175</itextId>
      <c_DistrictID>Sanga</c_DistrictID>
      <name>G16</name>
    </item>
    <item>
      <itextId>/data/c_ClusterID:option176</itextId>
      <c_DistrictID>Sanga</c_DistrictID>
      <name>G17</name>
    </item>
    <item>
      <itextId>/data/c_ClusterID:option177</itextId>
      <c_DistrictID>Sanga</c_DistrictID>
      <name>G18</name>
    </item>
    <item>
      <itextId>/data/c_ClusterID:option178</itextId>
      <c_DistrictID>Sanga</c_DistrictID>
      <name>G19</name>
    </item>
    <item>
      <itextId>/data/c_ClusterID:option179</itextId>
      <c_DistrictID>Sanga</c_DistrictID>
      <name>G20</name>
    </item>
  </root>
</instance>

      <bind nodeset="/data/meta/instanceID" type="string" readonly="true()" calculate="concat('uuid:', uuid())"/>
      <bind nodeset="/data/c_StartTime" type="dateTime" jr:preload="timestamp" jr:preloadParams="start"/>
      <bind nodeset="/data/c_EndTime" type="dateTime" jr:preload="timestamp" jr:preloadParams="end"/>
      <bind nodeset="/data/c_RecorderID" type="int" required="true()" maxLength="2" constraint="regex(., '^[0-9]{2}$')" jr:constraintMsg="Invalid. Recorder ID code is 2 numbers long."/>
      <bind nodeset="/data/c_DistrictID" type="select1" required="true()" db_add_col_1="."/>
      <bind nodeset="/data/c_ClusterID" type="select1" required="true()" db_add_col_1="/data/c_DistrictID" db_add_col_2="." />
      <bind nodeset="/data/c_ClusterName" type="string" required="true()" relevant="(string-length(/data/c_ClusterID) > 3)" />
      <bind nodeset="/data/c_GPS" type="geopoint" required="true()"/>
      <bind nodeset="/data/c_VillagePop" type="int" required="true()"/>
      <bind nodeset="/data/c_BlackFly" type="select1" required="true()"/>
      <bind nodeset="/data/c_ClusterNotes" type="string"/>
    </model>
  </h:head>
  <h:body>
    <input ref="/data/c_RecorderID">
      <label ref="jr:itext('/data/c_RecorderID:label')"/>
      <hint ref="jr:itext('/data/c_RecorderID:hint')"/>
    </input>

    <!-- District Begin -->
    <!-- District label End -->

<select1 ref="/data/c_DistrictID">
  <label ref="jr:itext('/data/c_DistrictID:label')"/>
  <item>
    <label ref="jr:itext('/data/c_DistrictID/Cahora-Bassa:label')"/>
    <value>Cahora-Bassa</value>
  </item>
  <item>
    <label ref="jr:itext('/data/c_DistrictID/Lago:label')"/>
    <value>Lago</value>
  </item>
  <item>
    <label ref="jr:itext('/data/c_DistrictID/Maravia:label')"/>
    <value>Maravia</value>
  </item>
  <item>
    <label ref="jr:itext('/data/c_DistrictID/Mecanhelas:label')"/>
    <value>Mecanhelas</value>
  </item>
  <item>
    <label ref="jr:itext('/data/c_DistrictID/Milange:label')"/>
    <value>Milange</value>
  </item>
  <item>
    <label ref="jr:itext('/data/c_DistrictID/Morrumbala:label')"/>
    <value>Morrumbala</value>
  </item>
  <item>
    <label ref="jr:itext('/data/c_DistrictID/Sanga:label')"/>
    <value>Sanga</value>
  </item>
  <item>
    <label ref="jr:itext('/data/c_DistrictID/Outro distrito:label')"/>
    <value>Outro distrito</value>
  </item>
</select1>

    <!-- EU label End -->

    <select1 ref="/data/c_ClusterID">
            <label ref="jr:itext('/data/c_ClusterID:label')"/>
            <itemset nodeset="instance('clusters')/root/item[c_DistrictID= /data/c_DistrictID ]">
                <value ref="name"/>
                <label ref="jr:itext(itextId)"/>
            </itemset>
    </select1>



    <input ref="/data/c_ClusterName">
      <label ref="jr:itext('/data/c_ClusterName:label')"/>
    </input>

    <!-- <input ref="/data/c_ClusterID">
      <label ref="jr:itext('/data/c_ClusterID:label')"/>
      <hint ref="jr:itext('/data/c_ClusterID:hint')"/>
    </input> -->
    <input ref="/data/c_GPS">
      <label ref="jr:itext('/data/c_GPS:label')"/>
      <hint ref="jr:itext('/data/c_GPS:hint')"/>
    </input>
    <input ref="/data/c_VillagePop">
      <label ref="jr:itext('/data/c_VillagePop:label')"/>
      <hint ref="jr:itext('/data/c_VillagePop:hint')"/>
    </input>
    <select1 ref="/data/c_BlackFly">
      <label ref="jr:itext('/data/c_BlackFly:label')"/>
      <item>
        <label ref="jr:itext('/data/c_BlackFly:option0')"/>
        <value>Yes</value>
      </item>
      <item>
        <label ref="jr:itext('/data/c_BlackFly:option1')"/>
        <value>No</value>
      </item>
      <item>
        <label ref="jr:itext('/data/c_BlackFly:option2')"/>
        <value>DontKnow</value>
      </item>
    </select1>
    <input ref="/data/c_ClusterNotes">
      <label ref="jr:itext('/data/c_ClusterNotes:label')"/>
    </input>
  </h:body>
</h:html>
